horn/__init__.py
horn/path.py
horn/tpl.py
horn/cli/__init__.py
horn/cli/api.py
horn/cli/model.py
horn/cli/new.py
horn/cli/repo.py
horn/cli/schema.py
horn/templates/gen/tests/views/test_{{ singular }}.py.jinja
horn/templates/gen/{{ app }}/models/{{ singular }}.py.jinja
horn/templates/gen/{{ app }}/schemas/{{ singular }}.py.jinja
horn/templates/gen/{{ app }}/views/{{ singular }}.py.jinja
horn/templates/new/.gitignore.jinja
horn/templates/new/MANIFEST.in
horn/templates/new/README.md.jinja
horn/templates/new/logging.ini.jinja
horn/templates/new/pyproject.toml.jinja
horn/templates/new/setup.cfg
horn/templates/new/setup.py.jinja
horn/templates/new/instance/prod.secret.cfg.jinja
horn/templates/new/log/.gitkeep
horn/templates/new/tests/__init__.py
horn/templates/new/tests/conftest.py.jinja
horn/templates/new/tests/factories.py.jinja
horn/templates/new/tests/test_swagger.py
horn/templates/new/tests/views/__init__.py
horn/templates/new/tests/views/test_home.py
horn/templates/new/tests/views/test_session.py
horn/templates/new/tests/views/test_user.py
horn/templates/new/{{ app }}/__init__.py
horn/templates/new/{{ app }}/cmds.py
horn/templates/new/{{ app }}/exts.py.jinja
horn/templates/new/{{ app }}/helpers.py.jinja
horn/templates/new/{{ app }}/router.py.jinja
horn/templates/new/{{ app }}/run.py.jinja
horn/templates/new/{{ app }}/swagger.py.jinja
horn/templates/new/{{ app }}/config/__init__.py
horn/templates/new/{{ app }}/config/default.py.jinja
horn/templates/new/{{ app }}/config/development.py.jinja
horn/templates/new/{{ app }}/config/production.py
horn/templates/new/{{ app }}/config/testing.py.jinja
horn/templates/new/{{ app }}/core/__init__.py.jinja
horn/templates/new/{{ app }}/core/database.py.jinja
horn/templates/new/{{ app }}/core/errors.py.jinja
horn/templates/new/{{ app }}/core/schema.py.jinja
horn/templates/new/{{ app }}/models/__init__.py.jinja
horn/templates/new/{{ app }}/models/helpers.py.jinja
horn/templates/new/{{ app }}/models/user.py.jinja
horn_py-0.6.5.dist-info/METADATA
horn_py-0.6.5.dist-info/WHEEL
horn_py-0.6.5.dist-info/entry_points.txt
horn_py-0.6.5.dist-info/licenses/LICENSE
horn_py-0.6.5.dist-info/RECORD
