Metadata-Version: 2.1
Name: horn-py
Version: 0.6.5
Summary: A Flask scaffolding tool
Project-URL: Documentation, https://bigfang.github.io/horn-py
Project-URL: Source code, https://github.com/bigfang/horn-py
Author-email: bigfang <bitair@gmail.com>
License-File: LICENSE
Classifier: License :: OSI Approved :: MIT License
Classifier: Programming Language :: Python :: 3.7
Classifier: Programming Language :: Python :: 3.8
Classifier: Programming Language :: Python :: 3.9
Classifier: Programming Language :: Python :: 3.10
Classifier: Programming Language :: Python :: 3.11
Classifier: Programming Language :: Python :: Implementation :: CPython
Classifier: Programming Language :: Python :: Implementation :: PyPy
Classifier: Topic :: Utilities
Requires-Python: >=3.7
Requires-Dist: copier>=8.1.0
Requires-Dist: docopt>=0.6
Requires-Dist: inflection>=0.5.1
Requires-Dist: pampy>=0.3.0
Requires-Dist: toml>=0.10.2
